setup.py
better_verilog/__init__.py
better_verilog/__main__.py
better_verilog/ast.py
better_verilog/eval.py
better_verilog/gen_verilog.py
better_verilog/parser.py
better_verilog/sema.py
better_verilog.egg-info/PKG-INFO
better_verilog.egg-info/SOURCES.txt
better_verilog.egg-info/dependency_links.txt
better_verilog.egg-info/entry_points.txt
better_verilog.egg-info/requires.txt
better_verilog.egg-info/top_level.txt
test/test.py