Metadata-Version: 1.0
Name: better-verilog
Version: 0.1
Summary: A translactor from better_verilog HDL to pure verilog.
Home-page: https://github.com/avakar/better_verilog
Author: Martin Vejnár
Author-email: avakar@ratatanek.cz
License: MIT
Platform: UNKNOWN
